sintautils/__init__.py
sintautils/backend.py
sintautils/core.py
sintautils/exceptions.py
sintautils-0.0.2.dist-info/LICENSE
sintautils-0.0.2.dist-info/METADATA
sintautils-0.0.2.dist-info/WHEEL
sintautils-0.0.2.dist-info/top_level.txt
sintautils-0.0.2.dist-info/RECORD
