Metadata-Version: 2.2
Name: sintautils
Version: 0.0.2
Summary: Python utility package for retrieving and synchronizing data on SINTA (Science and Technology Index)
Home-page: https://github.com/groaking/sintautils
Author: Samarthya Lykamanuella
Author-email: lykamanuella@outlook.com
Maintainer: Samarthya Lykamanuella
Maintainer-email: lykamanuella@outlook.com
License: GNU General Public License v3.0 or later
Project-URL: Bug Reports, https://github.com/groaking/sintautils/issues
Project-URL: GitHub, https://github.com/groaking/sintautils
Project-URL: Home Page, https://github.com/groaking/sintautils
Project-URL: Change Log, https://github.com/groaking/sintautils/blob/main/CHANGELOG.md
Keywords: sinta,kemendikbud,scraper,automation,dikti,ristekdikti,kemdikbud,kemenristek,kemeristekdikti,synchronization,tools,administrator,admin
Classifier: Development Status :: 3 - Alpha
Classifier: Intended Audience :: Developers
Classifier: Intended Audience :: System Administrators
Classifier: Topic :: Database
Classifier: Topic :: File Formats :: JSON
Classifier: Topic :: Software Development :: Libraries
Classifier: Topic :: Utilities
Classifier: License :: OSI Approved :: GNU General Public License v3 or later (GPLv3+)
Classifier: Programming Language :: Python :: 3
Classifier: Programming Language :: Python :: 3.9
Classifier: Programming Language :: Python :: 3.10
Classifier: Programming Language :: Python :: 3.11
Classifier: Programming Language :: Python :: 3.12
Classifier: Programming Language :: Python :: 3.13
Classifier: Programming Language :: Python :: 3.14
Classifier: Environment :: Console
Requires-Python: >=3.9
License-File: LICENSE
Requires-Dist: lxml
Requires-Dist: openpyxl
Requires-Dist: requests
Dynamic: author
Dynamic: author-email
Dynamic: classifier
Dynamic: description
Dynamic: description-content-type
Dynamic: home-page
Dynamic: keywords
Dynamic: license
Dynamic: maintainer
Dynamic: maintainer-email
Dynamic: project-url
Dynamic: requires-dist
Dynamic: requires-python
Dynamic: summary
